easy_choose/__init__.py
easy_choose/chooser.py
easy_choose/tests.py
easy_choose-1.1.3.dist-info/METADATA
easy_choose-1.1.3.dist-info/WHEEL
easy_choose-1.1.3.dist-info/licenses/LICENSE
easy_choose-1.1.3.dist-info/RECORD
