Metadata-Version: 2.1
Name: easy-choose
Version: 1.1.3
Summary: It can easily help you choose!
Project-URL: Homepage, https://github.com/Raskora/easy-choose
Project-URL: Bug Tracker, https://github.com/Raskora/easy-choose/issues
Author-email: Raskora <Raskora@outlook.com>
License: MIT License
Classifier: License :: OSI Approved :: MIT License
Classifier: Operating System :: OS Independent
Classifier: Programming Language :: Python :: 3
Requires-Python: >=3.7
